compiler/rtl/ram.v
////////////////////////////////////////////////////////////////////////////////////
// File Name: ram.v
// Author: Sung Min Kim
// Email: sungk9@uw.edu
//
// Copyright (c) 2012-2016 University of Washington
// All rights reserved.
//
// Redistribution and use in source and binary forms, with or without modification,
// are permitted provided that the following conditions are met:
// -       Redistributions of source code must retain the above copyright notice,
//         this list of conditions and the following disclaimer.
// -       Redistributions in binary form must reproduce the above copyright notice,
//         this list of conditions and the following disclaimer in the documentation
//         and/or other materials provided with the distribution.
// -       Neither the name of the University of Washington nor the names of its
//         contributors may be used to endorse or promote products derived from this
//         software without specific prior written permission.
//
// THIS SOFTWARE IS PROVIDED BY THE UNIVERSITY OF WASHINGTON AND CONTRIBUTORS "AS IS"
// AND ANY EXPRESS OR IMPLIED WARRANTIES, INCLUDING, BUT NOT LIMITED TO, THE IMPLIED
// WARRANTIES OF MERCHANTABILITY AND FITNESS FOR A PARTICULAR PURPOSE ARE DISCLAIMED.
// IN NO EVENT SHALL THE UNIVERSITY OF WASHINGTON OR CONTRIBUTORS BE LIABLE FOR ANY
// DIRECT, INDIRECT, INCIDENTAL, SPECIAL, EXEMPLARY, OR CONSEQUENTIAL DAMAGES
// (INCLUDING, BUT NOT LIMITED TO, PROCUREMENT OF SUBSTITUTE GOODS OR SERVICES; LOSS
// OF USE, DATA, OR PROFITS; OR BUSINESS INTERRUPTION) HOWEVER CAUSED AND ON ANY
// THEORY OF LIABILITY, WHETHER IN CONTRACT, STRICT LIABILITY, OR TORT (INCLUDING
// NEGLIGENCE OR OTHERWISE) ARISING IN ANY WAY OUT OF THE USE OF THIS SOFTWARE, EVEN
// IF ADVISED OF THE POSSIBILITY OF SUCH DAMAGE.
////////////////////////////////////////////////////////////////////////////////////

`timescale 1ns / 1ps

// Ram module for NPU memories,
// to be used during synthesis testing
//
// MEMSEL_W number of MSB's are used to select the memory,
// and the remaining REGSEL_W number of bits are used for
// addressing registers
//

module ram #(
  parameter DEPTH = 2048,
  parameter WIDTH = 16,
  parameter MEMSEL_W = 3,
  parameter REGSEL_W = 11,
  parameter MEM_ADDR = 3'b000
)(
  dout,
  mem_adr,
  reg_adr,
  clk,
  din,
  we
);

// Outputs
output [WIDTH-1:0]    dout;    // RAM data output

// Inputs
input [MEMSEL_W-1:0]  mem_adr; // memory selection address
input [REGSEL_W-1:0]  reg_adr; // register selection address
input                 clk;     // clock
input [WIDTH-1:0]     din;     // mem data input
input                 we;      // write enable (active high)

// synopsys translate_off

// RAM
reg   [WIDTH-1:0] mem [0:DEPTH-1];

// RAM write behavior
always @(posedge clk) begin
  if (mem_adr == MEM_ADDR && reg_adr <= DEPTH && we) begin
    mem[reg_adr] <= din;
  end else begin
    mem[reg_adr] <= mem[reg_adr];
  end
end

// RAM read behavior
reg [WIDTH-1:0] dout_reg;
always @(posedge clk) begin
  if (reg_adr <= DEPTH-1) dout_reg <= mem[reg_adr];
  else                    dout_reg <= {WIDTH{1'bx}};
end

// Output assignment
assign dout = dout_reg;

// synopsys translate_on

endmodule

compiler/rtl/sigmoid_lut.v
////////////////////////////////////////////////////////////////////////////////////
// File Name: sigmoid_lut.v
// Author: Thierry Moreau
// Email: moreau@uw.edu
//
// Copyright (c) 2012-2016 University of Washington
// All rights reserved.
//
// Redistribution and use in source and binary forms, with or without modification,
// are permitted provided that the following conditions are met:
// -       Redistributions of source code must retain the above copyright notice,
//         this list of conditions and the following disclaimer.
// -       Redistributions in binary form must reproduce the above copyright notice,
//         this list of conditions and the following disclaimer in the documentation
//         and/or other materials provided with the distribution.
// -       Neither the name of the University of Washington nor the names of its
//         contributors may be used to endorse or promote products derived from this
//         software without specific prior written permission.
//
// THIS SOFTWARE IS PROVIDED BY THE UNIVERSITY OF WASHINGTON AND CONTRIBUTORS "AS IS"
// AND ANY EXPRESS OR IMPLIED WARRANTIES, INCLUDING, BUT NOT LIMITED TO, THE IMPLIED
// WARRANTIES OF MERCHANTABILITY AND FITNESS FOR A PARTICULAR PURPOSE ARE DISCLAIMED.
// IN NO EVENT SHALL THE UNIVERSITY OF WASHINGTON OR CONTRIBUTORS BE LIABLE FOR ANY
// DIRECT, INDIRECT, INCIDENTAL, SPECIAL, EXEMPLARY, OR CONSEQUENTIAL DAMAGES
// (INCLUDING, BUT NOT LIMITED TO, PROCUREMENT OF SUBSTITUTE GOODS OR SERVICES; LOSS
// OF USE, DATA, OR PROFITS; OR BUSINESS INTERRUPTION) HOWEVER CAUSED AND ON ANY
// THEORY OF LIABILITY, WHETHER IN CONTRACT, STRICT LIABILITY, OR TORT (INCLUDING
// NEGLIGENCE OR OTHERWISE) ARISING IN ANY WAY OUT OF THE USE OF THIS SOFTWARE, EVEN
// IF ADVISED OF THE POSSIBILITY OF SUCH DAMAGE.
////////////////////////////////////////////////////////////////////////////////////

`timescale 1ns / 1ps

module sigmoid_lut (
    input clk,
    input rst_n,
    input [SIGMODE_W-1:0] mode,
    input [ACC_WIDTH-1:0] din,
    output reg [7:0] dout,
    // ram-specific ports
    input [RAMDATA_W-1:0] ram_din,
    input [REGSEL_W-1:0]  ram_reg_adr,
    input [MEMSEL_W-1:0]  ram_mem_adr,
    input                 ram_we
);

    // Include parameters
  `include "params.inc"  

    // Sigmoid registers
    reg [SIGMODE_W-1:0] mode_dly;
    reg [DATA_WIDTH-1:0] d_small;
    reg NE;
    reg PSM;
    reg NSM;
    reg POF;
    reg NOF;

    // Steepness
    wire [ACC_WIDTH-1:0] scaled_din;
    assign scaled_din = {{SIG_LSHIFT{din[ACC_WIDTH-1]}},{din[ACC_WIDTH-1:SIG_LSHIFT]}};

    wire [INDEX_WIDTH-1:0] lut_index;
    assign lut_index = scaled_din[ACC_WIDTH-1:PRECISION_SHIFT];

    // ===================
    // Sigmoid RAM
    // ===================
    wire [DATA_WIDTH-1:0]       lut_dout;
    reg  [REGSEL_W-1:0]         reg_adr;
    wire [MEMSEL_W-1:0]         mem_adr = ram_mem_adr;
    // RAM address mux
    always @(*) begin
        if (ram_we)  reg_adr = ram_reg_adr;
        else         reg_adr = lut_index[LOG_SIG_LUT_DEPTH-1:0];
    end
    // RAM instantiation
    ram #(
        .WIDTH(DATA_WIDTH),
        .DEPTH(SIG_LUT_DEPTH),
        .MEMSEL_W(MEMSEL_W),
        .REGSEL_W(REGSEL_W),
        .MEM_ADDR(SIG_RAM_ADR)
    ) sig_lut (
        .clk(clk),
        .mem_adr(mem_adr),
        .reg_adr(reg_adr),
        .din(ram_din[DATA_WIDTH-1:0]),
        .we(ram_we),
        .dout(lut_dout)
    );

    // Main Datapath
    always @ (posedge clk) begin
        if (rst_n == 1'b0) begin
            mode_dly <= 0;
            d_small <= 0;
            NE <= 0;
            PSM <= 0;
            NSM <= 0;
            POF <= 0;
            NOF <= 0;
        end else begin
            // latch mode
            mode_dly <= mode;

            // latch input
            d_small <= scaled_din[DATA_WIDTH+SIG_IN_PREC-SIG_OUT_PREC-1:SIG_IN_PREC-SIG_OUT_PREC];

            // positive overflow flag
            if ( !lut_index[17] && |lut_index[16:8])
                POF <= 1'b1;
            else
                POF <= 1'b0;
            // negative overflow flag
            if (lut_index[17] && ~&lut_index[16:8])
                NOF <= 1'b1;
            else
                NOF <= 1'b0;
            // positive small value flag
            if ($signed(lut_index) < PCUTOFF)
                PSM <= 1'b1;
            else
                PSM <= 1'b0;
            // positive small value flag
            if ($signed(lut_index) > NCUTOFF)
                NSM <= 1'b1;
            else
                NSM <= 1'b0;
            // negative flag
            NE <= din[ACC_WIDTH-1];
        end
    end

    // Used for non-symmetrical sigmoid
    wire [DATA_WIDTH:0] dout_p1;
    assign dout_p1 = {lut_dout[DATA_WIDTH-1],lut_dout[DATA_WIDTH-1:0]}+ONE;
    wire [DATA_WIDTH:0] dsmall_p1;
    assign dsmall_p1 = {d_small[DATA_WIDTH-1],d_small[DATA_WIDTH-1:0]}+ONE;

    // Output logic
    // Change output to be combinational reg
    // always @ (posedge clk) begin
    always @ (*) begin
        if (rst_n == 1'b0)
            dout = 0;
        else begin
            if (mode_dly[1:0] == SIGMODE_SYMMETRIC) begin
                if (POF == 1'b1)
                    dout = MAXVAL;
                else if (NOF == 1'b1)
                    dout = MINVAL;
                else if ((PSM==1'b1 & NE==1'b0) | (NSM==1'b1 & NE==1'b1))
                    dout = d_small;
                else
                    dout = lut_dout;
            end else if (mode_dly[1:0] == SIGMODE_SIGMOID) begin
                if (POF == 1'b1)
                    dout = MAXVAL;
                else if (NOF == 1'b1)
                    dout = 0;
                else if ((PSM==1'b1 & NE==1'b0) | (NSM==1'b1 & NE==1'b1))
                    dout = {1'b0, dsmall_p1[DATA_WIDTH-1:1]};
                else
                    dout = {1'b0, dout_p1[DATA_WIDTH-1:1]};
            end else begin // assume it is linear
                dout = d_small;
            end
        end
    end

endmodule

compiler/sim/sigmoid_lut/sigmoid_lut_tb.v
////////////////////////////////////////////////////////////////////////////////
// File Name: sigmoid_lut_tb.v
// Author: Thierry Moreau
// Email: moreau@uw.edu
//
// Copyright (c) 2012-2016 University of Washington
// All rights reserved.
//
// Redistribution and use in source and binary forms, with or without modification,
// are permitted provided that the following conditions are met:
// -       Redistributions of source code must retain the above copyright notice,
//         this list of conditions and the following disclaimer.
// -       Redistributions in binary form must reproduce the above copyright notice,
//         this list of conditions and the following disclaimer in the documentation
//         and/or other materials provided with the distribution.
// -       Neither the name of the University of Washington nor the names of its
//         contributors may be used to endorse or promote products derived from this
//         software without specific prior written permission.
//
// THIS SOFTWARE IS PROVIDED BY THE UNIVERSITY OF WASHINGTON AND CONTRIBUTORS "AS IS"
// AND ANY EXPRESS OR IMPLIED WARRANTIES, INCLUDING, BUT NOT LIMITED TO, THE IMPLIED
// WARRANTIES OF MERCHANTABILITY AND FITNESS FOR A PARTICULAR PURPOSE ARE DISCLAIMED.
// IN NO EVENT SHALL THE UNIVERSITY OF WASHINGTON OR CONTRIBUTORS BE LIABLE FOR ANY
// DIRECT, INDIRECT, INCIDENTAL, SPECIAL, EXEMPLARY, OR CONSEQUENTIAL DAMAGES
// (INCLUDING, BUT NOT LIMITED TO, PROCUREMENT OF SUBSTITUTE GOODS OR SERVICES; LOSS
// OF USE, DATA, OR PROFITS; OR BUSINESS INTERRUPTION) HOWEVER CAUSED AND ON ANY
// THEORY OF LIABILITY, WHETHER IN CONTRACT, STRICT LIABILITY, OR TORT (INCLUDING
// NEGLIGENCE OR OTHERWISE) ARISING IN ANY WAY OUT OF THE USE OF THIS SOFTWARE, EVEN
// IF ADVISED OF THE POSSIBILITY OF SUCH DAMAGE.
////////////////////////////////////////////////////////////////////////////////////

`timescale 1ns / 1ps
`define VCD_DUMP

module sigmoid_lut_tb;

    // Include parameter file
    `include "params.inc"

    localparam SIG_INPUT_WIDTH  = ACC_WIDTH;
    localparam SIG_OUTPUT_WIDTH = DATA_WIDTH;

    // Inputs
    reg CLK;
    reg RST_N;
    reg [RAMDATA_W-1:0] ram_din;
    reg [REGSEL_W-1:0] ram_reg_adr;
    reg [MEMSEL_W-1:0] ram_mem_adr;
    reg ram_we;

    // Outputs
    wire [SIG_OUTPUT_WIDTH-1:0] data_out;

    // Simulation variables
    integer i;

    // SRAM and indices
    reg [SIG_INPUT_WIDTH-1:0] inputs [SIGTB_TEST_SIZE-1:0];
    reg [SIG_OUTPUT_WIDTH-1:0] outputs [SIGTB_TEST_SIZE-1:0];
    reg [SIG_OUTPUT_WIDTH-1:0] sigmoid [SIG_LUT_DEPTH-1:0];
    reg [SIGTB_LOG_TEST_SIZE-1:0] inDataIdx;
    reg [SIGTB_LOG_TEST_SIZE-1:0] outDataIdx;
    reg [LOG_SIG_LUT_DEPTH-1:0] sigDataIdx;

    // SRAM outputs
    wire [SIG_INPUT_WIDTH-1:0] inData = inputs[inDataIdx];
    wire [SIG_OUTPUT_WIDTH-1:0] outData = outputs[outDataIdx];
    wire [SIG_OUTPUT_WIDTH-1:0] sigData = sigmoid[sigDataIdx];

    // Instantiate the Unit Under Test (UUT)
    sigmoid_lut uut (
        .clk(CLK),
        .rst_n(RST_N),
        .mode({1'b0, SIGMODE_SYMMETRIC}),
        .din(inData),
        .dout(data_out),
        .ram_din(ram_din),
        .ram_reg_adr(ram_reg_adr),
        .ram_mem_adr(ram_mem_adr),
        .ram_we(ram_we)
    );

    // clock generation
    always begin
        #(PER/2) CLK =~ CLK;
    end

    always @ ( posedge CLK ) begin
        $display("time = %d",$time);
        $display("inData = %x",inData);
        $display("data_out = %x",data_out);
    end

    initial begin

        `ifdef VCD_DUMP
            $dumpfile("sigmoid_lut_tb.vcd");
            $dumpvars;
            $dumpon;
        `endif
        `ifdef VPD_DUMP
            $vcdplusfile("sigmoid_lut_tb.vpd");
            $vcdpluson();
        `endif

        // Initialize memory
        $readmemh("sig_input.mif", inputs);
        $readmemh("sig_output.mif", outputs);
        $readmemh("sigmoid.mif", sigmoid);

        // Initialize Inputs
        CLK = 1;
        RST_N = 0;
        ram_din = 0;
        ram_reg_adr = 0;
        ram_mem_adr = 0;
        ram_we = 0;
        sigDataIdx = 0;
        inDataIdx = 0;
        outDataIdx = 0;

        // Global reset
        #(PER)
        RST_N = 1;

        // Wait 10 periods for global reset to finish
        #(PER*10);

//`ifdef READ_WRITE_MEMORY
        $display("Loading sigmoid LUT contents");
        // Load the Sigmoid SRAM
        for (i = 0; i < SIG_LUT_DEPTH-1; i = i+1) begin
            #(PER);
            ram_we = 1;
            ram_mem_adr = SIG_RAM_ADR;
            sigDataIdx = sigDataIdx + 1;
            ram_din = sigData;
            ram_reg_adr = sigDataIdx;
        end
        #(PER)
        ram_we = 0;
//`endif

        // Start recording
        $display("Simulation start!");
        `ifdef DEBUG
            $display("\t\ttime,\tidx\tdin,\tlut_idx\tdout\tref");
            $monitor("%d,\t%d,\t%h,\t%d\t%h\t%h",$time,inDataIdx,inData,uut.lut_index,data_out,outData);
        `endif
        for (i = 0; i < SIGTB_TEST_SIZE+SIGTB_UUT_DELAY; i = i+1) begin
            #(PER);
            if (i < SIGTB_TEST_SIZE-1) begin
                inDataIdx = inDataIdx + 1;
            end
            if (i >= SIGTB_UUT_DELAY) begin
                outDataIdx = inDataIdx - SIGTB_UUT_DELAY;
            end else begin
                outDataIdx = 0;
            end
            if (data_out !== outData) begin
                $display ("ERROR at time %d", $time);
                $display ("\tExpected value %h, Got Value %h", outData, data_out);
                // $finish;
            end
        end

        #(PER*10);
        $display ("Simulation Completed! SUCCESS!!!");
        `ifdef VCD_DUMP
            $dumpoff;
        `endif
        `ifdef VPD_DUMP
            $vcdplusoff;
        `endif
        $finish;

    end

endmodule

compiler/sim/sigmoid_lut/sigmoid_lut_tb.vcd
$date
	Wed Jun  1 19:36:25 2016
$end
$version
	Icarus Verilog
$end
$timescale
	1ps
$end
$scope module sigmoid_lut_tb $end
$var wire 26 ! inData [25:0] $end
$var wire 8 " outData [7:0] $end
$var wire 8 # sigData [7:0] $end
$var wire 8 $ data_out [7:0] $end
$var reg 1 % CLK $end
$var reg 1 & RST_N $end
$var reg 8 ' inDataIdx [7:0] $end
$var reg 8 ( outDataIdx [7:0] $end
$var reg 21 ) ram_din [20:0] $end
$var reg 6 * ram_mem_adr [5:0] $end
$var reg 14 + ram_reg_adr [13:0] $end
$var reg 1 , ram_we $end
$var reg 9 - sigDataIdx [8:0] $end
$var integer 32 . i [31:0] $end
$scope module uut $end
$var wire 1 % clk $end
$var wire 26 / din [25:0] $end
$var wire 6 0 mem_adr [5:0] $end
$var wire 3 1 mode [2:0] $end
$var wire 21 2 ram_din [20:0] $end
$var wire 6 3 ram_mem_adr [5:0] $end
$var wire 14 4 ram_reg_adr [13:0] $end
$var wire 1 , ram_we $end
$var wire 1 & rst_n $end
$var wire 26 5 scaled_din [25:0] $end
$var wire 18 6 lut_index [17:0] $end
$var wire 8 7 lut_dout [7:0] $end
$var wire 9 8 dsmall_p1 [8:0] $end
$var wire 9 9 dout_p1 [8:0] $end
$var reg 1 : NE $end
$var reg 1 ; NOF $end
$var reg 1 < NSM $end
$var reg 1 = POF $end
$var reg 1 > PSM $end
$var reg 8 ? d_small [7:0] $end
$var reg 8 @ dout [7:0] $end
$var reg 3 A mode_dly [2:0] $end
$var reg 14 B reg_adr [13:0] $end
$scope module sig_lut $end
$var wire 1 % clk $end
$var wire 8 C din [7:0] $end
$var wire 6 D mem_adr [5:0] $end
$var wire 14 E reg_adr [13:0] $end
$var wire 1 , we $end
$var wire 8 F dout [7:0] $end
$var reg 8 G dout_reg [7:0] $end
$upscope $end
$upscope $end
$upscope $end
$enddefinitions $end
#0
$dumpvars
bx G
bx F
b0 E
b0 D
b0 C
b0 B
b0 A
b0 @
b0 ?
0>
0=
0<
0;
0:
bx 9
b10000000 8
bx 7
b0 6
b0 5
b0 4
b0 3
b0 2
b11 1
b0 0
b0 /
bx .
b0 -
0,
b0 +
b0 *
b0 )
b0 (
b0 '
0&
1%
b0 $
b0 #
b0 "
b0 !
$end
#5000
0%
#10000
1<
1>
b11 A
1%
1&
#15000
0%
#20000
1%
#25000
0%
#30000
1%
#35000
0%
#40000
1%
#45000
0%
#50000
1%
#55000
0%
#60000
1%
#65000
0%
#70000
1%
#75000
0%
#80000
1%
#85000
0%
#90000
1%
#95000
0%
#100000
1%
#105000
0%
#110000
1%
b0 .
#115000
0%
#120000
b10 C
b1 B
b1 E
1%
b1 .
b1 +
b1 4
b10 )
b10 2
b10 #
b1 -
b10 0
b10 D
b10 *
b10 3
1,
#125000
0%
#130000
b10 B
b10 E
b100 C
1%
b10 .
b10 +
b10 4
b100 )
b100 2
b100 #
b10 -
#135000
0%
#140000
b11 B
b11 E
b110 C
1%
b11 .
b11 +
b11 4
b110 )
b110 2
b110 #
b11 -
#145000
0%
#150000
b100 B
b100 E
b1000 C
1%
b100 .
b100 +
b100 4
b1000 )
b1000 2
b1000 #
b100 -
#155000
0%
#160000
b101 B
b101 E
b1010 C
1%
b101 .
b101 +
b101 4
b1010 )
b1010 2
b1010 #
b101 -
#165000
0%
#170000
b110 B
b110 E
b1100 C
1%
b110 .
b110 +
b110 4
b1100 )
b1100 2
b1100 #
b110 -
#175000
0%
#180000
b111 B
b111 E
b1110 C
1%
b111 .
b111 +
b111 4
b1110 )
b1110 2
b1110 #
b111 -
#185000
0%
#190000
b1000 B
b1000 E
b10000 C
1%
b1000 .
b1000 +
b1000 4
b10000 )
b10000 2
b10000 #
b1000 -
#195000
0%
#200000
b1001 B
b1001 E
b10010 C
1%
b1001 .
b1001 +
b1001 4
b10010 )
b10010 2
b10010 #
b1001 -
#205000
0%
#210000
b1010 B
b1010 E
b10100 C
1%
b1010 .
b1010 +
b1010 4
b10100 )
b10100 2
b10100 #
b1010 -
#215000
0%
#220000
b1011 B
b1011 E
b10110 C
1%
b1011 .
b1011 +
b1011 4
b10110 )
b10110 2
b10110 #
b1011 -
#225000
0%
#230000
b1100 B
b1100 E
b11000 C
1%
b1100 .
b1100 +
b1100 4
b11000 )
b11000 2
b11000 #
b1100 -
#235000
0%
#240000
b1101 B
b1101 E
b11010 C
1%
b1101 .
b1101 +
b1101 4
b11010 )
b11010 2
b11010 #
b1101 -
#245000
0%
#250000
b1110 B
b1110 E
b11100 C
1%
b1110 .
b1110 +
b1110 4
b11100 )
b11100 2
b11100 #
b1110 -
#255000
0%
#260000
b1111 B
b1111 E
b11110 C
1%
b1111 .
b1111 +
b1111 4
b11110 )
b11110 2
b11110 #
b1111 -
#265000
0%
#270000
b10000 B
b10000 E
b100000 C
1%
b10000 .
b10000 +
b10000 4
b100000 )
b100000 2
b100000 #
b10000 -
#275000
0%
#280000
b10001 B
b10001 E
b100010 C
1%
b10001 .
b10001 +
b10001 4
b100010 )
b100010 2
b100010 #
b10001 -
#285000
0%
#290000
b10010 B
b10010 E
b100100 C
1%
b10010 .
b10010 +
b10010 4
b100100 )
b100100 2
b100100 #
b10010 -
#295000
0%
#300000
b10011 B
b10011 E
b100101 C
1%
b10011 .
b10011 +
b10011 4
b100101 )
b100101 2
b100101 #
b10011 -
#305000
0%
#310000
b10100 B
b10100 E
b100111 C
1%
b10100 .
b10100 +
b10100 4
b100111 )
b100111 2
b100111 #
b10100 -
#315000
0%
#320000
b10101 B
b10101 E
b101001 C
1%
b10101 .
b10101 +
b10101 4
b101001 )
b101001 2
b101001 #
b10101 -
#325000
0%
#330000
b10110 B
b10110 E
b101011 C
1%
b10110 .
b10110 +
b10110 4
b101011 )
b101011 2
b101011 #
b10110 -
#335000
0%
#340000
b10111 B
b10111 E
b101100 C
1%
b10111 .
b10111 +
b10111 4
b101100 )
b101100 2
b101100 #
b10111 -
#345000
0%
#350000
b11000 B
b11000 E
b101110 C
1%
b11000 .
b11000 +
b11000 4
b101110 )
b101110 2
b101110 #
b11000 -
#355000
0%
#360000
b11001 B
b11001 E
b110000 C
1%
b11001 .
b11001 +
b11001 4
b110000 )
b110000 2
b110000 #
b11001 -
#365000
0%
#370000
b11010 B
b11010 E
b110010 C
1%
b11010 .
b11010 +
b11010 4
b110010 )
b110010 2
b110010 #
b11010 -
#375000
0%
#380000
b11011 B
b11011 E
b110011 C
1%
b11011 .
b11011 +
b11011 4
b110011 )
b110011 2
b110011 #
b11011 -
#385000
0%
#390000
b11100 B
b11100 E
b110101 C
1%
b11100 .
b11100 +
b11100 4
b110101 )
b110101 2
b110101 #
b11100 -
#395000
0%
#400000
b11101 B
b11101 E
b110111 C
1%
b11101 .
b11101 +
b11101 4
b110111 )
b110111 2
b110111 #
b11101 -
#405000
0%
#410000
b11110 B
b11110 E
b111000 C
1%
b11110 .
b11110 +
b11110 4
b111000 )
b111000 2
b111000 #
b11110 -
#415000
0%
#420000
b11111 B
b11111 E
b111010 C
1%
b11111 .
b11111 +
b11111 4
b111010 )
b111010 2
b111010 #
b11111 -
#425000
0%
#430000
b100000 B
b100000 E
b111011 C
1%
b100000 .
b100000 +
b100000 4
b111011 )
b111011 2
b111011 #
b100000 -
#435000
0%
#440000
b100001 B
b100001 E
b111101 C
1%
b100001 .
b100001 +
b100001 4
b111101 )
b111101 2
b111101 #
b100001 -
#445000
0%
#450000
b100010 B
b100010 E
b111111 C
1%
b100010 .
b100010 +
b100010 4
b111111 )
b111111 2
b111111 #
b100010 -
#455000
0%
#460000
b100011 B
b100011 E
b1000000 C
1%
b100011 .
b100011 +
b100011 4
b1000000 )
b1000000 2
b1000000 #
b100011 -
#465000
0%
#470000
b100100 B
b100100 E
b1000001 C
1%
b100100 .
b100100 +
b100100 4
b1000001 )
b1000001 2
b1000001 #
b100100 -
#475000
0%
#480000
b100101 B
b100101 E
b1000011 C
1%
b100101 .
b100101 +
b100101 4
b1000011 )
b1000011 2
b1000011 #
b100101 -
#485000
0%
#490000
b100110 B
b100110 E
b1000100 C
1%
b100110 .
b100110 +
b100110 4
b1000100 )
b1000100 2
b1000100 #
b100110 -
#495000
0%
#500000
b100111 B
b100111 E
b1000110 C
1%
b100111 .
b100111 +
b100111 4
b1000110 )
b1000110 2
b1000110 #
b100111 -
#505000
0%
#510000
b101000 B
b101000 E
b1000111 C
1%
b101000 .
b101000 +
b101000 4
b1000111 )
b1000111 2
b1000111 #
b101000 -
#515000
0%
#520000
b101001 B
b101001 E
b1001001 C
1%
b101001 .
b101001 +
b101001 4
b1001001 )
b1001001 2
b1001001 #
b101001 -
#525000
0%
#530000
b101010 B
b101010 E
b1001010 C
1%
b101010 .
b101010 +
b101010 4
b1001010 )
b1001010 2
b1001010 #
b101010 -
#535000
0%
#540000
b101011 B
b101011 E
b1001011 C
1%
b101011 .
b101011 +
b101011 4
b1001011 )
b1001011 2
b1001011 #
b101011 -
#545000
0%
#550000
b101100 B
b101100 E
b1001100 C
1%
b101100 .
b101100 +
b101100 4
b1001100 )
b1001100 2
b1001100 #
b101100 -
#555000
0%
#560000
b101101 B
b101101 E
b1001110 C
1%
b101101 .
b101101 +
b101101 4
b1001110 )
b1001110 2
b1001110 #
b101101 -
#565000
0%
#570000
b101110 B
b101110 E
b1001111 C
1%
b101110 .
b101110 +
b101110 4
b1001111 )
b1001111 2
b1001111 #
b101110 -
#575000
0%
#580000
b101111 B
b101111 E
b1010000 C
1%
b101111 .
b101111 +
b101111 4
b1010000 )
b1010000 2
b1010000 #
b101111 -
#585000
0%
#590000
b110000 B
b110000 E
b1010001 C
1%
b110000 .
b110000 +
b110000 4
b1010001 )
b1010001 2
b1010001 #
b110000 -
#595000
0%
#600000
b110001 B
b110001 E
b1010011 C
1%
b110001 .
b110001 +
b110001 4
b1010011 )
b1010011 2
b1010011 #
b110001 -
#605000
0%
#610000
b110010 B
b110010 E
b1010100 C
1%
b110010 .
b110010 +
b110010 4
b1010100 )
b1010100 2
b1010100 #
b110010 -
#615000
0%
#620000
b110011 B
b110011 E
b1010101 C
1%
b110011 .
b110011 +
b110011 4
b1010101 )
b1010101 2
b1010101 #
b110011 -
#625000
0%
#630000
b110100 B
b110100 E
b1010110 C
1%
b110100 .
b110100 +
b110100 4
b1010110 )
b1010110 2
b1010110 #
b110100 -
#635000
0%
#640000
b110101 B
b110101 E
b1010111 C
1%
b110101 .
b110101 +
b110101 4
b1010111 )
b1010111 2
b1010111 #
b110101 -
#645000
0%
#650000
b110110 B
b110110 E
b1011000 C
1%
b110110 .
b110110 +
b110110 4
b1011000 )
b1011000 2
b1011000 #
b110110 -
#655000
0%
#660000
b110111 B
b110111 E
b1011001 C
1%
b110111 .
b110111 +
b110111 4
b1011001 )
b1011001 2
b1011001 #
b110111 -
#665000
0%
#670000
b111000 B
b111000 E
b1011010 C
1%
b111000 .
b111000 +
b111000 4
b1011010 )
b1011010 2
b1011010 #
b111000 -
#675000
0%
#680000
b111001 B
b111001 E
b1011011 C
1%
b111001 .
b111001 +
b111001 4
b1011011 )
b1011011 2
b1011011 #
b111001 -
#685000
0%
#690000
b111010 B
b111010 E
b1011100 C
1%
b111010 .
b111010 +
b111010 4
b1011100 )
b1011100 2
b1011100 #
b111010 -
#695000
0%
#700000
b111011 B
b111011 E
b1011101 C
1%
b111011 .
b111011 +
b111011 4
b1011101 )
b1011101 2
b1011101 #
b111011 -
#705000
0%
#710000
b111100 B
b111100 E
b1011110 C
1%
b111100 .
b111100 +
b111100 4
b1011110 )
b1011110 2
b1011110 #
b111100 -
#715000
0%
#720000
b111101 B
b111101 E
b1011111 C
1%
b111101 .
b111101 +
b111101 4
b1011111 )
b1011111 2
b1011111 #
b111101 -
#725000
0%
#730000
b111110 B
b111110 E
b1100000 C
1%
b111110 .
b111110 +
b111110 4
b1100000 )
b1100000 2
b1100000 #
b111110 -
#735000
0%
#740000
b111111 B
b111111 E
b1100001 C
1%
b111111 .
b111111 +
b111111 4
b1100001 )
b1100001 2
b1100001 #
b111111 -
#745000
0%
#750000
b1000000 B
b1000000 E
1%
b1000000 .
b1000000 +
b1000000 4
b1000000 -
#755000
0%
#760000
b1000001 B
b1000001 E
b1100010 C
1%
b1000001 .
b1000001 +
b1000001 4
b1100010 )
b1100010 2
b1100010 #
b1000001 -
#765000
0%
#770000
b1000010 B
b1000010 E
b1100011 C
1%
b1000010 .
b1000010 +
b1000010 4
b1100011 )
b1100011 2
b1100011 #
b1000010 -
#775000
0%
#780000
b1000011 B
b1000011 E
b1100100 C
1%
b1000011 .
b1000011 +
b1000011 4
b1100100 )
b1100100 2
b1100100 #
b1000011 -
#785000
0%
#790000
b1000100 B
b1000100 E
b1100101 C
1%
b1000100 .
b1000100 +
b1000100 4
b1100101 )
b1100101 2
b1100101 #
b1000100 -
#795000
0%
#800000
b1000101 B
b1000101 E
1%
b1000101 .
b1000101 +
b1000101 4
b1000101 -
#805000
0%
#810000
b1000110 B
b1000110 E
b1100110 C
1%
b1000110 .
b1000110 +
b1000110 4
b1100110 )
b1100110 2
b1100110 #
b1000110 -
#815000
0%
#820000
b1000111 B
b1000111 E
b1100111 C
1%
b1000111 .
b1000111 +
b1000111 4
b1100111 )
b1100111 2
b1100111 #
b1000111 -
#825000
0%
#830000
b1001000 B
b1001000 E
1%
b1001000 .
b1001000 +
b1001000 4
b1001000 -
#835000
0%
#840000
b1001001 B
b1001001 E
b1101000 C
1%
b1001001 .
b1001001 +
b1001001 4
b1101000 )
b1101000 2
b1101000 #
b1001001 -
#845000
0%
#850000
b1001010 B
b1001010 E
b1101001 C
1%
b1001010 .
b1001010 +
b1001010 4
b1101001 )
b1101001 2
b1101001 #
b1001010 -
#855000
0%
#860000
b1001011 B
b1001011 E
1%
b1001011 .
b1001011 +
b1001011 4
b1001011 -
#865000
0%
#870000
b1001100 B
b1001100 E
b1101010 C
1%
b1001100 .
b1001100 +
b1001100 4
b1101010 )
b1101010 2
b1101010 #
b1001100 -
#875000
0%
#880000
b1001101 B
b1001101 E
b1101011 C
1%
b1001101 .
b1001101 +
b1001101 4
b1101011 )
b1101011 2
b1101011 #
b1001101 -
#885000
0%
#890000
b1001110 B
b1001110 E
1%
b1001110 .
b1001110 +
b1001110 4
b1001110 -
#895000
0%
#900000
b1001111 B
b1001111 E
b1101100 C
1%
b1001111 .
b1001111 +
b1001111 4
b1101100 )
b1101100 2
b1101100 #
b1001111 -
#905000
0%
#910000
b1010000 B
b1010000 E
1%
b1010000 .
b1010000 +
b1010000 4
b1010000 -
#915000
0%
#920000
b1010001 B
b1010001 E
b1101101 C
1%
b1010001 .
b1010001 +
b1010001 4
b1101101 )
b1101101 2
b1101101 #
b1010001 -
#925000
0%
#930000
b1010010 B
b1010010 E
1%
b1010010 .
b1010010 +
b1010010 4
b1010010 -
#935000
0%
#940000
b1010011 B
b1010011 E
b1101110 C
1%
b1010011 .
b1010011 +
b1010011 4
b1101110 )
b1101110 2
b1101110 #
b1010011 -
#945000
0%
#950000
b1010100 B
b1010100 E
1%
b1010100 .
b1010100 +
b1010100 4
b1010100 -
#955000
0%
